irene_crypto-0.1.1.dist-info/METADATA
irene_crypto-0.1.1.dist-info/WHEEL
irene_crypto/__init__.py
irene_crypto/irene_crypto.pyd
irene_crypto-0.1.1.dist-info/RECORD
